COPYING
MANIFEST.in
README.md
setup.cfg
setup.py
json_rpc_django.egg-info/PKG-INFO
json_rpc_django.egg-info/SOURCES.txt
json_rpc_django.egg-info/dependency_links.txt
json_rpc_django.egg-info/not-zip-safe
json_rpc_django.egg-info/requires.txt
json_rpc_django.egg-info/top_level.txt
jsonrpc/__init__.py
jsonrpc/_json.py
jsonrpc/_types.py
jsonrpc/exceptions.py
jsonrpc/mochikit.py
jsonrpc/proxy.py
jsonrpc/site.py
jsonrpc/utils.py
jsonrpc/views.py
jsonrpc/templates/browse.html